petrosa_otel/__init__.py
petrosa_otel/instrumentors.py
petrosa_otel/logging_handlers.py
petrosa_otel/processors.py
petrosa_otel/setup.py
petrosa_otel-1.0.0.dist-info/METADATA
petrosa_otel-1.0.0.dist-info/WHEEL
petrosa_otel-1.0.0.dist-info/top_level.txt
petrosa_otel-1.0.0.dist-info/RECORD
