Metadata-Version: 2.4
Name: petrosa-otel
Version: 1.0.0
Summary: Unified OpenTelemetry initialization for Petrosa services
Author-email: Petrosa Team <dev@petrosa.com>
Project-URL: Homepage, https://github.com/PetroSa2/petrosa-otel
Project-URL: Repository, https://github.com/PetroSa2/petrosa-otel
Classifier: Development Status :: 4 - Beta
Classifier: Intended Audience :: Developers
Classifier: Programming Language :: Python :: 3
Classifier: Programming Language :: Python :: 3.11
Classifier: Programming Language :: Python :: 3.12
Requires-Python: >=3.11
Requires-Dist: opentelemetry-api>=1.20.0
Requires-Dist: opentelemetry-sdk>=1.20.0
Requires-Dist: opentelemetry-exporter-otlp-proto-grpc>=1.20.0
Requires-Dist: opentelemetry-instrumentation-logging>=0.41b0
Requires-Dist: opentelemetry-instrumentation-requests>=0.41b0
Requires-Dist: opentelemetry-instrumentation-urllib3>=0.41b0
Provides-Extra: fastapi
Requires-Dist: opentelemetry-instrumentation-fastapi>=0.41b0; extra == "fastapi"
Provides-Extra: mysql
Requires-Dist: opentelemetry-instrumentation-pymysql>=0.41b0; extra == "mysql"
Provides-Extra: mongodb
Requires-Dist: opentelemetry-instrumentation-pymongo>=0.41b0; extra == "mongodb"
Provides-Extra: all
Requires-Dist: petrosa-otel[fastapi,mongodb,mysql]; extra == "all"
Provides-Extra: dev
Requires-Dist: pytest>=7.0.0; extra == "dev"
Requires-Dist: pytest-asyncio>=0.21.0; extra == "dev"
Requires-Dist: pytest-cov>=4.0.0; extra == "dev"
Requires-Dist: ruff>=0.1.0; extra == "dev"
